PlanetLink/__init__.py
PlanetLink/wxBot.py
PlanetLink/wxMessage.py
PlanetLink-0.0.2.dist-info/LICENSE
PlanetLink-0.0.2.dist-info/METADATA
PlanetLink-0.0.2.dist-info/WHEEL
PlanetLink-0.0.2.dist-info/top_level.txt
PlanetLink-0.0.2.dist-info/RECORD
