Metadata-Version: 2.1
Name: PlanetLink
Version: 0.0.2
Summary: A pypi package to send message in different mediums.
Home-page: https://github.com/vu1nex/PlanetLink
Author: vu1nex
Author-email: me@vu1nex.com
Keywords: wx,wechat,bot,message,reminder
Classifier: Intended Audience :: Developers
Classifier: Programming Language :: Python :: 3
Classifier: License :: OSI Approved :: MIT License
Classifier: Operating System :: Unix
Classifier: Operating System :: MacOS :: MacOS X
Classifier: Operating System :: Microsoft :: Windows
License-File: LICENSE
